graphfusionai/__init__.py
graphfusionai/agent.py
graphfusionai/communication.py
graphfusionai/knowledge_graph.py
graphfusionai/memory.py
graphfusionai/ontology.py
graphfusionai/orchestration.py
graphfusionai/task_orchestrator.py
graphfusionai/team.py
graphfusionai/llm/__init__.py
graphfusionai/llm/base.py
graphfusionai/llm/conversation.py
graphfusionai/llm/llm_agent.py
graphfusionai/llm/mock_llm_agent.py
graphfusionai/llm/prompt_manager.py
graphfusionai/llm/providers/custom_aiml.py
graphfusionai/llm/providers/openai.py
graphfusionai/memory/__init__.py
graphfusionai/memory/base.py
graphfusionai/memory/vectorstore.py
graphfusionai/tools/__init__.py
graphfusionai/tools/base.py
graphfusionai/tools/loader.py
graphfusionai/tools/registry.py
graphfusionai/tools/validator.py
graphfusionai-0.1.2.dist-info/METADATA
graphfusionai-0.1.2.dist-info/WHEEL
graphfusionai-0.1.2.dist-info/licenses/LICENSE
graphfusionai-0.1.2.dist-info/RECORD
